arglib/__init__.py
arglib/ai/__init__.py
arglib/ai/assumptions.py
arglib/ai/claim_types.py
arglib/ai/credibility.py
arglib/ai/edge_validation.py
arglib/ai/evaluation.py
arglib/ai/llm.py
arglib/ai/miner.py
arglib/ai/mining.py
arglib/algorithms/__init__.py
arglib/algorithms/basics.py
arglib/cli/__init__.py
arglib/cli/main.py
arglib/core/__init__.py
arglib/core/bundles.py
arglib/core/evidence.py
arglib/core/graph.py
arglib/core/relations.py
arglib/core/spans.py
arglib/core/units.py
arglib/core/warrants.py
arglib/critique/__init__.py
arglib/critique/assumptions.py
arglib/critique/fragility.py
arglib/critique/patterns.py
arglib/data/__init__.py
arglib/data/argument_graph.schema.json
arglib/data/patterns_bank.yaml
arglib/integrations/__init__.py
arglib/io/__init__.py
arglib/io/json.py
arglib/io/schema.py
arglib/reasoning/__init__.py
arglib/reasoning/credibility.py
arglib/reasoning/explain.py
arglib/reasoning/reasoner.py
arglib/reasoning/warrant_gated.py
arglib/viz/__init__.py
arglib/viz/graphviz.py
arglib-0.1.11.dist-info/licenses/LICENSE
arglib-0.1.11.dist-info/METADATA
arglib-0.1.11.dist-info/WHEEL
arglib-0.1.11.dist-info/entry_points.txt
arglib-0.1.11.dist-info/top_level.txt
arglib-0.1.11.dist-info/RECORD
