Metadata-Version: 2.4
Name: arglib
Version: 0.1.11
Summary: Build a general-purpose, batteries-included Python library for creating, importing, analyzing, and reasoning over argument graphs derived from text and multimodal evidence.
License-Expression: MIT
Project-URL: Repository, https://github.com/vasanthsarathy/arglib
Requires-Python: >=3.11
License-File: LICENSE
Dynamic: license-file
